datadog_checks/__init__.py
datadog_checks/config.py
datadog_checks/errors.py
datadog_checks/log.py
datadog_checks/py.typed
datadog_checks/base/__about__.py
datadog_checks/base/__init__.py
datadog_checks/base/__init__.pyi
datadog_checks/base/agent.py
datadog_checks/base/config.py
datadog_checks/base/constants.py
datadog_checks/base/errors.py
datadog_checks/base/log.py
datadog_checks/base/types.py
datadog_checks/base/checks/__init__.py
datadog_checks/base/checks/__init__.pyi
datadog_checks/base/checks/_config_ast.py
datadog_checks/base/checks/base.py
datadog_checks/base/checks/db.py
datadog_checks/base/checks/network.py
datadog_checks/base/checks/kube_leader/__init__.py
datadog_checks/base/checks/kube_leader/__init__.pyi
datadog_checks/base/checks/kube_leader/base_check.py
datadog_checks/base/checks/kube_leader/mixins.py
datadog_checks/base/checks/kube_leader/record.py
datadog_checks/base/checks/kubelet_base/__init__.py
datadog_checks/base/checks/kubelet_base/__init__.pyi
datadog_checks/base/checks/kubelet_base/base.py
datadog_checks/base/checks/libs/__init__.py
datadog_checks/base/checks/libs/prometheus.py
datadog_checks/base/checks/libs/thread_pool.py
datadog_checks/base/checks/libs/timer.py
datadog_checks/base/checks/libs/vmware/__init__.py
datadog_checks/base/checks/libs/vmware/all_metrics.py
datadog_checks/base/checks/libs/vmware/basic_metrics.py
datadog_checks/base/checks/logs/__init__.py
datadog_checks/base/checks/logs/crawler/__init__.py
datadog_checks/base/checks/logs/crawler/base.py
datadog_checks/base/checks/logs/crawler/stream.py
datadog_checks/base/checks/openmetrics/__init__.py
datadog_checks/base/checks/openmetrics/__init__.pyi
datadog_checks/base/checks/openmetrics/base_check.py
datadog_checks/base/checks/openmetrics/mixins.py
datadog_checks/base/checks/openmetrics/v2/__init__.py
datadog_checks/base/checks/openmetrics/v2/base.py
datadog_checks/base/checks/openmetrics/v2/first_scrape_handler.py
datadog_checks/base/checks/openmetrics/v2/labels.py
datadog_checks_base-37.27.1.dist-info/METADATA
datadog_checks_base-37.27.1.dist-info/WHEEL
datadog_checks_base-37.27.1.dist-info/RECORD
