Metadata-Version: 2.4
Name: datadog-checks-base
Version: 37.27.1
Summary: The Datadog Check Toolkit
Project-URL: Source, https://github.com/DataDog/integrations-core
Author-email: Datadog <packages@datadoghq.com>
License-Expression: BSD-3-Clause
Keywords: agent,checks,datadog
Classifier: Development Status :: 5 - Production/Stable
Classifier: Intended Audience :: Developers
Classifier: Intended Audience :: System Administrators
Classifier: License :: OSI Approved :: BSD License
Classifier: Programming Language :: Python :: 3.13
Classifier: Topic :: System :: Monitoring
Provides-Extra: db
Requires-Dist: mmh3==5.2.0; extra == 'db'
Provides-Extra: deps
Requires-Dist: binary==1.0.2; extra == 'deps'
Requires-Dist: cachetools==6.2.0; extra == 'deps'
Requires-Dist: cryptography==45.0.6; extra == 'deps'
Requires-Dist: ddtrace==3.16.4; extra == 'deps'
Requires-Dist: jellyfish==1.2.0; extra == 'deps'
Requires-Dist: lazy-loader==0.4; extra == 'deps'
Requires-Dist: prometheus-client==0.22.1; extra == 'deps'
Requires-Dist: protobuf==6.32.0; extra == 'deps'
Requires-Dist: pydantic==2.11.7; extra == 'deps'
Requires-Dist: python-dateutil==2.9.0.post0; extra == 'deps'
Requires-Dist: pywin32==311; (sys_platform == 'win32') and extra == 'deps'
Requires-Dist: pyyaml==6.0.2; extra == 'deps'
Requires-Dist: requests-toolbelt==1.0.0; extra == 'deps'
Requires-Dist: requests-unixsocket2==1.0.0; extra == 'deps'
Requires-Dist: requests==2.32.5; extra == 'deps'
Requires-Dist: simplejson==3.20.1; extra == 'deps'
Requires-Dist: urllib3==2.6.3; extra == 'deps'
Requires-Dist: wrapt==1.17.3; extra == 'deps'
Provides-Extra: http
Requires-Dist: aws-requests-auth==0.4.3; extra == 'http'
Requires-Dist: botocore==1.40.21; extra == 'http'
Requires-Dist: oauthlib==3.3.1; extra == 'http'
Requires-Dist: pyjwt==2.10.1; extra == 'http'
Requires-Dist: pyopenssl==25.1.0; extra == 'http'
Requires-Dist: pysocks==1.7.1; extra == 'http'
Requires-Dist: requests-kerberos==0.15.0; extra == 'http'
Requires-Dist: requests-ntlm==1.3.0; extra == 'http'
Requires-Dist: requests-oauthlib==2.0.0; extra == 'http'
Provides-Extra: json
Requires-Dist: orjson==3.11.3; extra == 'json'
Provides-Extra: kube
Requires-Dist: kubernetes==33.1.0; extra == 'kube'
Requires-Dist: requests-oauthlib==2.0.0; extra == 'kube'
